edison_mcp/__init__.py
edison_mcp/server.py
edison_mcp-0.2.7.dist-info/WHEEL
edison_mcp-0.2.7.dist-info/entry_points.txt
edison_mcp-0.2.7.dist-info/METADATA
edison_mcp-0.2.7.dist-info/RECORD
