Metadata-Version: 2.3
Name: edison-mcp
Version: 0.2.7
Summary: MCP server for Edison Scientific platform integration (former FutureHouse)
Author: Newton Winter
Author-email: Newton Winter <isoutthere@gmail.com>
Requires-Dist: eliot>=1.17.5
Requires-Dist: pycomfort>=0.0.18
Requires-Dist: fastmcp[tasks]>=3.0.0b1
Requires-Dist: fastapi>=0.115.13
Requires-Dist: httpx>=0.25.0
Requires-Dist: pydantic>=2.0.0
Requires-Dist: typer>=0.9.0
Requires-Dist: python-dotenv>=1.0.0
Requires-Dist: pandas>=2.0.0
Requires-Dist: biopython>=1.84
Requires-Dist: typer>=0.16.0
Requires-Dist: simtk>=0.1.0
Requires-Dist: openmm>=8.3.0
Requires-Dist: py3dmol>=2.5.0
Requires-Dist: smithery>=0.4.2
Requires-Dist: ruff>=0.14.0
Requires-Dist: edison-client>=0.8.4
Requires-Dist: coredis>=5.6.0
Requires-Python: >=3.11
